{
    "game_name": "Maco",
    "heuristic_name": "Simple",
    "player1_name": "Genetic",
    "player2_name": "GreedyAction",
    "n_games": 10,
    "budget": 5,
    "wins1": 0,
    "wins2": 7,
    "ties": 3,
    "player_1_forward_model_visits": 23977.9,
    "player_1_visited_states": 0.0,
    "player_2_forward_model_visits": 1164.1,
    "player_2_visited_states": 807.8,
    "p_value": 0.0010320139151629437,
    "processing_time": 331.7984929084778,
    "date": "2024-06-18",
    "hour": "10:19:12"
}