{
    "game_name": "Maco",
    "heuristic_name": "Simple",
    "player1_name": "GreedyAction",
    "player2_name": "BridgeBurningMontecarloTreeSearch",
    "n_games": 100,
    "budget": 1,
    "wins1": 81,
    "wins2": 8,
    "ties": 11,
    "player_1_forward_model_visits": 0.0,
    "player_1_visited_states": 0.0,
    "player_2_forward_model_visits": 848.92,
    "player_2_visited_states": 979.02,
    "p_value": 0.0,
    "processing_time": 499.2066731452942,
    "date": "2024-06-07",
    "hour": "02:11:35"
}