{
    "game_name": "Maco",
    "heuristic_name": "Simple",
    "player1_name": "GreedyAction",
    "player2_name": "Genetic",
    "n_games": 100,
    "budget": 5,
    "wins1": 74,
    "wins2": 16,
    "ties": 10,
    "player_1_forward_model_visits": 0.0,
    "player_1_visited_states": 0.0,
    "player_2_forward_model_visits": 7810.08,
    "player_2_visited_states": 4662.95,
    "p_value": 2.220446049250313e-16,
    "processing_time": 2512.625832080841,
    "date": "2024-06-15",
    "hour": "04:03:17"
}