{
    "game_name": "Maco",
    "heuristic_name": "Simple",
    "player1_name": "OnlineEvolution",
    "player2_name": "Random",
    "n_games": 10,
    "budget": 5,
    "wins1": 7,
    "wins2": 0,
    "ties": 3,
    "player_1_forward_model_visits": 25683.9,
    "player_1_visited_states": 75.1,
    "player_2_forward_model_visits": 0.0,
    "player_2_visited_states": 0.0,
    "p_value": 0.0010320139151629437,
    "processing_time": 314.11137318611145,
    "date": "2024-05-27",
    "hour": "01:19:05"
}